pyramid_dynamodb_sessions.py
pyramid_dynamodb_sessions-0.1.3.dist-info/LICENSE
pyramid_dynamodb_sessions-0.1.3.dist-info/METADATA
pyramid_dynamodb_sessions-0.1.3.dist-info/WHEEL
pyramid_dynamodb_sessions-0.1.3.dist-info/top_level.txt
pyramid_dynamodb_sessions-0.1.3.dist-info/RECORD
